WhenWasThat/__init__.py
WhenWasThat/when.py
whenwasthat-0.1.1.dist-info/licenses/LICENSE
whenwasthat-0.1.1.dist-info/METADATA
whenwasthat-0.1.1.dist-info/WHEEL
whenwasthat-0.1.1.dist-info/top_level.txt
whenwasthat-0.1.1.dist-info/RECORD
