Metadata-Version: 2.4
Name: WhenWasThat
Version: 0.1.1
Summary: A small library for getting human readable time value.
Home-page: https://github.com/codefitz/WhenWasThat
Author: Wes Moskal-Fitzpatrick
Author-email: wes@traversys.io
Classifier: Programming Language :: Python :: 3
Classifier: License :: OSI Approved :: GNU General Public License v3 (GPLv3)
Classifier: Operating System :: OS Independent
Requires-Python: >=3.0
License-File: LICENSE
Requires-Dist: pandas
Dynamic: author
Dynamic: author-email
Dynamic: classifier
Dynamic: description
Dynamic: description-content-type
Dynamic: home-page
Dynamic: license-file
Dynamic: requires-dist
Dynamic: requires-python
Dynamic: summary
